[
  {
    "id": "base-life",
    "title": "🌱 Базовая жизнь",
    "description": "Самые нужные глаголы, чтобы выжить и говорить о себе, семье и быте.",
    "difficulty": "A1",
    "wave": 1,
    "verbs": [
      { "ka": "ყოფნა", "ru": "быть", "note": "глагол-связка" },
      { "ka": "ქონა", "ru": "иметь (вещи)" },
      { "ka": "ყოლა", "ru": "иметь (людей, животных)" },
      { "ka": "წასვლა", "ru": "идти, уходить" },
      { "ka": "მოსვლა", "ru": "приходить" },
      { "ka": "ჭამა", "ru": "есть" },
      { "ka": "დალევა", "ru": "пить" },
      { "ka": "ძილი", "ru": "спать" },
      { "ka": "მუშაობა", "ru": "работать" },
      { "ka": "სწავლა", "ru": "учиться" },
      { "ka": "ლაპარაკი", "ru": "говорить" },
      { "ka": "ყურება", "ru": "смотреть" },
      { "ka": "მოსმენა", "ru": "слушать" },
      { "ka": "კითხვის კითხვა", "ru": "спрашивать / читать" },
      { "ka": "წერა", "ru": "писать" },
      { "ka": "თქმა", "ru": "сказать" },
      { "ka": "ცხოვრება", "ru": "жить" },
      { "ka": "თამაში", "ru": "играть" },
      { "ka": "სვლა", "ru": "двигаться" },
      { "ka": "ჩაცმა", "ru": "одеваться" }
    ]
  },
  {
    "id": "movement-space",
    "title": "🌿 Движение и пространство",
    "description": "Глаголы направления, положения и перемещения. Основа логики приставок (შე-, ჩა-, გა-, ამ-, და-, გადა-).",
    "difficulty": "A2",
    "wave": 2,
    "verbs": [
      { "ka": "შესვლა", "ru": "входить" },
      { "ka": "გასვლა", "ru": "выходить" },
      { "ka": "ჩასვლა", "ru": "спускаться" },
      { "ka": "ამოსვლა", "ru": "подниматься" },
      { "ka": "გადასვლა", "ru": "переходить" },
      { "ka": "გადმოსვლა", "ru": "приходить обратно" },
      { "ka": "სიარული", "ru": "ходить, гулять" },
      { "ka": "სირბილი", "ru": "бегать" },
      { "ka": "დგომა", "ru": "стоять" },
      { "ka": "ჯდომა", "ru": "сидеть" },
      { "ka": "წოლა", "ru": "лежать" },
      { "ka": "მიდინება", "ru": "течь (о реке)" },
      { "ka": "ფრენა", "ru": "лететь" },
      { "ka": "გამოტანა", "ru": "выносить" },
      { "ka": "შეტანა", "ru": "вносить" },
      { "ka": "გადატანა", "ru": "переносить" },
      { "ka": "მიყვანა", "ru": "отводить" },
      { "ka": "მოყვანა", "ru": "приводить" },
      { "ka": "წასვლა", "ru": "уходить" },
      { "ka": "მოსვლა", "ru": "приходить" }
    ]
  },
  {
    "id": "emotions-state",
    "title": "🌺 Эмоции и состояние",
    "description": "Безличные глаголы чувств и состояния: нравится, лень, страшно, стыдно и т.п.",
    "difficulty": "A2",
    "wave": 3,
    "verbs": [
      { "ka": "მიყვარს", "ru": "я люблю" },
      { "ka": "მომწონს", "ru": "мне нравится" },
      { "ka": "მეზარება", "ru": "мне лень" },
      { "ka": "მრცხვენია", "ru": "мне стыдно" },
      { "ka": "მიკვირს", "ru": "мне удивительно" },
      { "ka": "მეშინია", "ru": "мне страшно" },
      { "ka": "მიხარია", "ru": "мне радостно" },
      { "ka": "მწყინს", "ru": "мне грустно" },
      { "ka": "მშია", "ru": "я голоден" },
      { "ka": "მეძინება", "ru": "хочу спать" },
      { "ka": "მწყურია", "ru": "хочу пить" },
      { "ka": "მავიწყდება", "ru": "забываю" },
      { "ka": "მახსოვს", "ru": "помню" },
      { "ka": "მინდა", "ru": "хочу" },
      { "ka": "შემიძლია", "ru": "могу" },
      { "ka": "მეჩქარება", "ru": "спешу" },
      { "ka": "მენატრება", "ru": "скучаю" },
      { "ka": "მეჩვენება", "ru": "мне кажется" },
      { "ka": "მეკარგება", "ru": "теряю" },
      { "ka": "მეყინება", "ru": "мне холодно" }
    ]
  },
  {
    "id": "mind-communication",
    "title": "🧠 Мысль и общение",
    "description": "Глаголы мышления, понимания, восприятия и общения.",
    "difficulty": "A2–B1",
    "wave": 4,
    "verbs": [
      { "ka": "ფიქრი", "ru": "думать" },
      { "ka": "ცოდნა", "ru": "знать" },
      { "ka": "გახსენება", "ru": "вспоминать" },
      { "ka": "გაგება", "ru": "понимать" },
      { "ka": "კითხვის დასმა", "ru": "спрашивать" },
      { "ka": "პასუხის გაცემა", "ru": "отвечать" },
      { "ka": "მოყოლა", "ru": "рассказывать" },
      { "ka": "ყურება", "ru": "смотреть" },
      { "ka": "მოსმენა", "ru": "слушать" },
      { "ka": "დანახვა", "ru": "увидеть" },
      { "ka": "დაფიქრება", "ru": "задуматься" },
      { "ka": "არჩევა", "ru": "выбирать" },
      { "ka": "განსჯა", "ru": "рассуждать" },
      { "ka": "სწავლა", "ru": "учиться" },
      { "ka": "სწავლება", "ru": "обучать" },
      { "ka": "გაგზავნა", "ru": "отправлять" },
      { "ka": "მიღება", "ru": "получать" },
      { "ka": "მოწვევა", "ru": "приглашать" },
      { "ka": "დარეკვა", "ru": "звонить" },
      { "ka": "წერა", "ru": "писать" }
    ]
  },
  {
    "id": "daily-routine",
    "title": "💼 Повседневная рутина",
    "description": "Бытовые и рутинные действия, повседневные фразы и привычки.",
    "difficulty": "A1–A2",
    "wave": 5,
    "verbs": [
      { "ka": "ადგომა", "ru": "вставать" },
      { "ka": "ჩაცმა", "ru": "одеваться" },
      { "ka": "დაბანა", "ru": "мыть" },
      { "ka": "გახეხვა", "ru": "чистить" },
      { "ka": "გარეცხვა", "ru": "стирать" },
      { "ka": "დალაგება", "ru": "убирать" },
      { "ka": "მომზადება", "ru": "готовить" },
      { "ka": "ჭამა", "ru": "есть" },
      { "ka": "სმა", "ru": "пить" },
      { "ka": "გასვლა", "ru": "выходить" },
      { "ka": "დაბრუნება", "ru": "возвращаться" },
      { "ka": "ყიდვა", "ru": "покупать" },
      { "ka": "გაყიდვა", "ru": "продавать" },
      { "ka": "წასვლა", "ru": "уходить" },
      { "ka": "მისვლა", "ru": "приходить" },
      { "ka": "დასვენება", "ru": "отдыхать" },
      { "ka": "ნახვა", "ru": "встречать / видеть" },
      { "ka": "დარეკვა", "ru": "звонить" },
      { "ka": "წერა", "ru": "писать" },
      { "ka": "კითხვა", "ru": "читать" }
    ]
  },
  {
    "id": "social-work",
    "title": "💬 Работа и общение",
    "description": "Рабочие и социальные глаголы: говорить, договариваться, помогать, решать.",
    "difficulty": "B1",
    "wave": 6,
    "verbs": [
      { "ka": "მუშაობა", "ru": "работать" },
      { "ka": "შეხვედრა", "ru": "встречаться" },
      { "ka": "გამართვა", "ru": "организовывать" },
      { "ka": "დაგეგმვა", "ru": "планировать" },
      { "ka": "გაგზავნა", "ru": "отправлять" },
      { "ka": "მიღება", "ru": "принимать / получать" },
      { "ka": "დარეკვა", "ru": "звонить" },
      { "ka": "ხელმოწერა", "ru": "подписывать" },
      { "ka": "გადახდა", "ru": "платить" },
      { "ka": "დახმარება", "ru": "помогать" },
      { "ka": "თქმა", "ru": "сказать" },
      { "ka": "შეთანხმება", "ru": "соглашаться" },
      { "ka": "დაპირება", "ru": "обещать" },
      { "ka": "განხილვა", "ru": "обсуждать" },
      { "ka": "გაგება", "ru": "понимать / договариваться" },
      { "ka": "მოწვევა", "ru": "приглашать" },
      { "ka": "გადაწყვეტა", "ru": "решать" },
      { "ka": "დამატება", "ru": "добавлять" },
      { "ka": "შეძლება", "ru": "мочь / быть способным" },
      { "ka": "დაგვიანება", "ru": "опаздывать" }
    ]
  },
  {
    "id": "prefix-logic",
    "title": "🚀 Логика приставок",
    "description": "Глубокое понимание смысловых приставок и направлений движения.",
    "difficulty": "B1–B2",
    "wave": 7,
    "verbs": [
      { "ka": "შესვლა", "ru": "войти (внутрь)" },
      { "ka": "გასვლა", "ru": "выйти (наружу)" },
      { "ka": "ჩასვლა", "ru": "спуститься вниз" },
      { "ka": "ამოსვლა", "ru": "подняться вверх" },
      { "ka": "გადასვლა", "ru": "перейти (через что-то)" },
      { "ka": "გადმოსვლა", "ru": "перейти обратно / сюда" },
      { "ka": "შეტანა", "ru": "внести (внутрь)" },
      { "ka": "გამოტანა", "ru": "вынести (наружу)" },
      { "ka": "გადატანა", "ru": "перенести (через)" },
      { "ka": "ჩატანა", "ru": "занести вниз" },
      { "ka": "ამოტანა", "ru": "поднять наверх" },
      { "ka": "დატანა", "ru": "положить / внести" },
      { "ka": "მიტანა", "ru": "донести / доставить" },
      { "ka": "მოტანა", "ru": "принести" },
      { "ka": "გატანა", "ru": "вынести" },
      { "ka": "წაღება", "ru": "унести" },
      { "ka": "შემოტანა", "ru": "принести внутрь" },
      { "ka": "გადმოტანა", "ru": "вынести сюда / на сторону говорящего" },
      { "ka": "შეტანა", "ru": "внести / вставить" },
      { "ka": "გადატანა", "ru": "переносить / перевести" }
    ]
  },
  {
    "id": "abstract-verbs",
    "title": "🪄 Абстрактные и служебные глаголы",
    "description": "Глаголы мышления, решений и действий над объектами.",
    "difficulty": "B1–B2",
    "wave": 8,
    "verbs": [
      { "ka": "დაწყება", "ru": "начинать" },
      { "ka": "დასრულება", "ru": "заканчивать" },
      { "ka": "გაგრძელება", "ru": "продолжать" },
      { "ka": "არჩევა", "ru": "выбирать" },
      { "ka": "გადაწყვეტა", "ru": "решать" },
      { "ka": "შეცვლა", "ru": "менять" },
      { "ka": "შენახვა", "ru": "сохранять" },
      { "ka": "წაშლა", "ru": "удалять" },
      { "ka": "ჩართვა", "ru": "включать" },
      { "ka": "გამორთვა", "ru": "выключать" },
      { "ka": "მიღწევა", "ru": "достигать" },
      { "ka": "დაკარგვა", "ru": "терять" },
      { "ka": "პოვნა", "ru": "находить" },
      { "ka": "შექმნა", "ru": "создавать" },
      { "ka": "განადგურება", "ru": "уничтожать" },
      { "ka": "მოფიქრება", "ru": "придумывать" },
      { "ka": "დაყენება", "ru": "ставить / устанавливать" },
      { "ka": "გაშვება", "ru": "запускать" },
      { "ka": "დახურვა", "ru": "закрывать" },
      { "ka": "გახსნა", "ru": "открывать" }
    ]
  }
]
