{
  "lesson_id": "pronoun-decl-4",
  "title": "3-е лицо множественное число — მესამე პირი მრავლობითი",
  "lexicon": [
    {"lemma": "ისინი", "ru": "они (именительный)"},
    {"lemma": "მათ", "ru": "они (эргатив/дательный)"},
    {"lemma": "მათი", "ru": "их (родительный)"},
    {"lemma": "მათით", "ru": "ими (творительный)"},
    {"lemma": "ესენი", "ru": "эти (именительный)"},
    {"lemma": "ამათ", "ru": "эти (эргатив/дательный)"},
    {"lemma": "ამათი", "ru": "этих (родительный)"},
    {"lemma": "მაგათ", "ru": "те (эргатив/дательный, средние)"},
    {"lemma": "მაგათი", "ru": "тех (родительный, средние)"}
  ],
  "questions": [
    {
      "id": "prd4_q01",
      "lemma": "ისინი",
      "question": "Какая эргативная форма у «ისინი» (они)?",
      "options": ["მათი", "მათ", "მათით"],
      "answer_index": 1,
      "explanation": "Эргативная форма «ისინი» — მათ. Эта же форма используется и в дательном.",
      "tags": ["declension"],
      "difficulty": 1
    },
    {
      "id": "prd4_q02",
      "lemma": "ისინი",
      "question": "Какая дательная форма у «ისინი»?",
      "options": ["მათი", "ისინი", "მათ"],
      "answer_index": 2,
      "explanation": "Дательная форма «ისინი» — მათ — совпадает с эргативной.",
      "tags": ["declension"],
      "difficulty": 1
    },
    {
      "id": "prd4_q03",
      "lemma": "მათი",
      "question": "Какая родительная форма у «ისინი»?",
      "options": ["მათ", "მათი", "მათით"],
      "answer_index": 1,
      "explanation": "Родительная форма «ისინი» — მათი — «их».",
      "tags": ["declension"],
      "difficulty": 1
    },
    {
      "id": "prd4_q04",
      "lemma": "მათით",
      "question": "Какая творительная форма у «ისინი»?",
      "options": ["მათი", "მათით", "მათად"],
      "answer_index": 1,
      "explanation": "Творительная форма «ისინი» — მათით — «ими».",
      "tags": ["declension"],
      "difficulty": 1
    },
    {
      "id": "prd4_q05",
      "lemma": "ესენი",
      "question": "Как будет множественное число от указательного «ეს» (именительный)?",
      "options": ["ესენი", "ამათ", "ამათი"],
      "answer_index": 0,
      "explanation": "Множественное от «ეს» в именительном — ესენი — «эти».",
      "tags": ["declension"],
      "difficulty": 1
    },
    {
      "id": "prd4_q06",
      "lemma": "ამათ",
      "question": "Какая эргативная форма у «ესენი»?",
      "options": ["ამათი", "ესენი", "ამათ"],
      "answer_index": 2,
      "explanation": "Эргативная форма «ესენი» — ამათ.",
      "tags": ["declension"],
      "difficulty": 1
    },
    {
      "id": "prd4_q07",
      "lemma": "ამათი",
      "question": "Какая родительная форма у «ესენი»?",
      "options": ["ამათი", "ამათ", "ამათით"],
      "answer_index": 0,
      "explanation": "Родительная форма «ესენი» — ამათი — «этих».",
      "tags": ["declension"],
      "difficulty": 1
    },
    {
      "id": "prd4_q08",
      "lemma": "მაგათ",
      "question": "Какая эргативная форма у множественного «ეგენი» (те, средние)?",
      "options": ["მაგათი", "მაგათ", "ეგენი"],
      "answer_index": 1,
      "explanation": "Эргативная форма множественного «ეგენი» — მაგათ.",
      "tags": ["declension"],
      "difficulty": 2
    },
    {
      "id": "prd4_q09",
      "lemma": "მაგათი",
      "question": "Какая родительная форма у «ეგენი»?",
      "options": ["მაგათ", "მაგათი", "მაგათით"],
      "answer_index": 1,
      "explanation": "Родительная форма «ეგენი» — მაგათი — «тех (средних)».",
      "tags": ["declension"],
      "difficulty": 2
    },
    {
      "id": "prd4_q10",
      "lemma": "მათ",
      "question": "Переведи: «მათ წიგნები იყიდეს»",
      "options": ["Они купили книги", "Их книги купили", "Им купили книги"],
      "answer_index": 0,
      "explanation": "მათ — эргатив от «ისინი». იყიდეს — «купили». «Они купили книги».",
      "tags": ["translation"],
      "difficulty": 2
    },
    {
      "id": "prd4_q11",
      "lemma": "მათი",
      "question": "Переведи: «მათი სახლი თბილისშია»",
      "options": ["Их дом в Тбилиси", "Им дом в Тбилиси", "Они в доме в Тбилиси"],
      "answer_index": 0,
      "explanation": "მათი — «их» (родительный). მათი სახლი — «их дом».",
      "tags": ["translation"],
      "difficulty": 2
    },
    {
      "id": "prd4_q12",
      "lemma": "მათ",
      "question": "Переведи: «მათ უყვართ საქართველო»",
      "options": ["Они любят Грузию", "Их любит Грузия", "Им нравится Грузия"],
      "answer_index": 2,
      "explanation": "მათ — дательная форма «ისინი». უყვართ требует дательного: «Им нравится Грузия».",
      "tags": ["translation"],
      "difficulty": 2
    },
    {
      "id": "prd4_q13",
      "lemma": "მათ",
      "question": "Какая особенность эргативной и дательной форм у «ისინი»?",
      "options": ["они разные", "они совпадают — обе მათ", "дательная отсутствует"],
      "answer_index": 1,
      "explanation": "У «ისინი» эргативная и дательная формы совпадают — обе მათ.",
      "tags": ["theory"],
      "difficulty": 2
    },
    {
      "id": "prd4_q14",
      "lemma": "ამათ",
      "question": "Вставь нужную форму: «___ გააკეთეს საჩუქარი» (эти сделали подарок)",
      "options": ["ესენი", "ამათი", "ამათ"],
      "answer_index": 2,
      "explanation": "გააკეთეს — аорист переходного глагола, подлежащее в эргативе: ამათ.",
      "tags": ["fill-in"],
      "difficulty": 2
    },
    {
      "id": "prd4_q15",
      "lemma": "მათი",
      "question": "Вставь нужную форму: «___ მასწავლებელი კარგია» (их учитель хороший)",
      "options": ["მათ", "მათი", "ისინი"],
      "answer_index": 1,
      "explanation": "Для принадлежности нужен родительный: მათი მასწავლებელი — «их учитель».",
      "tags": ["fill-in"],
      "difficulty": 2
    },
    {
      "id": "prd4_q16",
      "lemma": "ამათი",
      "question": "Вставь нужную форму: «___ ბავშვები სკოლაში არიან» (дети этих в школе)",
      "options": ["ამათ", "ესენი", "ამათი"],
      "answer_index": 2,
      "explanation": "Принадлежность выражается родительным: ამათი ბავშვები — «дети этих».",
      "tags": ["fill-in"],
      "difficulty": 2
    },
    {
      "id": "prd4_q17",
      "lemma": "მათ",
      "question": "Вставь нужную форму: «___ ეძინათ» (они спали)",
      "options": ["ისინი", "მათ", "მათი"],
      "answer_index": 1,
      "explanation": "ეძინათ (спали) — глагол состояния, требует дательного: მათ ეძინათ.",
      "tags": ["fill-in"],
      "difficulty": 2
    },
    {
      "id": "prd4_q18",
      "lemma": "მათით",
      "question": "Переведи: «მათით კმაყოფილი ვარ»",
      "options": ["Я ими доволен", "Они мной довольны", "Их довольно"],
      "answer_index": 0,
      "explanation": "მათით — «ими» (творительный). მათით კმაყოფილი ვარ — «Я ими доволен».",
      "tags": ["translation"],
      "difficulty": 2
    }
  ]
}
