{
  "lesson_id": "cafe-5",
  "title": "Повторение и диалоги — გამეორება",
  "lexicon": [
    {"lemma": "მენიუ", "ru": "меню"},
    {"lemma": "მინდა", "ru": "хочу"},
    {"lemma": "გემრიელი", "ru": "вкусный"},
    {"lemma": "რამდენი ღირს", "ru": "сколько стоит"},
    {"lemma": "გთხოვთ", "ru": "пожалуйста"},
    {"lemma": "მადლობა", "ru": "спасибо"},
    {"lemma": "ანგარიში", "ru": "счёт"},
    {"lemma": "მომიტანეთ", "ru": "принесите мне"}
  ],
  "questions": [
    {
      "id": "cafe5_q01",
      "lemma": "მენიუ",
      "question": "Ты сел за стол в ресторане. Что попросишь первым делом?",
      "options": ["მენიუ, გთხოვთ", "ანგარიში, გთხოვთ", "მადლობა"],
      "answer_index": 0,
      "explanation": "«მენიუ, გთხოვთ» — меню, пожалуйста. Первым делом просим меню!",
      "tags": ["context"],
      "difficulty": 1
    },
    {
      "id": "cafe5_q02",
      "lemma": "მინდა",
      "question": "Переведи диалог: Официант: «რა გინდათ?» — Что он спрашивает?",
      "options": ["Что вы хотите?", "Как дела?", "Откуда вы?"],
      "answer_index": 0,
      "explanation": "«რა გინდათ?» — Что вы хотите? რა — что, გინდათ — хотите (вежл.).",
      "tags": ["translation"],
      "difficulty": 2
    },
    {
      "id": "cafe5_q03",
      "lemma": "ყავა",
      "question": "Как заказать кофе с молоком? «ყავა ... , გთხოვთ»",
      "options": ["რძით", "წყლით", "შაქრით"],
      "answer_index": 0,
      "explanation": "«ყავა რძით» — кофе с молоком. რძე — молоко, რძით — с молоком.",
      "tags": ["phrase"],
      "difficulty": 2
    },
    {
      "id": "cafe5_q04",
      "lemma": "გემრიელი",
      "question": "Хозяин ресторана спрашивает, понравилась ли еда. Что ответишь?",
      "options": ["ძალიან გემრიელი იყო!", "ძალიან ცივი იყო!", "ძალიან ძვირი იყო!"],
      "answer_index": 0,
      "explanation": "«ძალიან გემრიელი იყო!» — было очень вкусно! იყო — было.",
      "tags": ["phrase"],
      "difficulty": 2
    },
    {
      "id": "cafe5_q05",
      "lemma": "ანგარიში",
      "question": "Обед закончен. Что попросишь у официанта?",
      "options": ["ანგარიში, გთხოვთ", "მენიუ, გთხოვთ", "წყალი, გთხოვთ"],
      "answer_index": 0,
      "explanation": "«ანგარიში, გთხოვთ» — счёт, пожалуйста.",
      "tags": ["context"],
      "difficulty": 1
    },
    {
      "id": "cafe5_q06",
      "lemma": "ცხელი",
      "question": "Переведи: «ცხელი ჩაი მინდა»",
      "options": ["хочу горячий чай", "хочу холодный чай", "хочу сладкий чай"],
      "answer_index": 0,
      "explanation": "«ცხელი ჩაი მინდა» — хочу горячий чай. ცხელი — горячий, ჩაი — чай.",
      "tags": ["translation"],
      "difficulty": 2
    },
    {
      "id": "cafe5_q07",
      "lemma": "რამდენი ღირს",
      "question": "Ты на рынке. Как спросить цену на сыр?",
      "options": ["ყველი რამდენი ღირს?", "ყველი სად არის?", "ყველი გინდათ?"],
      "answer_index": 0,
      "explanation": "«ყველი რამდენი ღირს?» — сколько стоит сыр?",
      "tags": ["phrase"],
      "difficulty": 2
    },
    {
      "id": "cafe5_q08",
      "lemma": "მომიტანეთ",
      "question": "Переведи: «მომიტანეთ ცივი წყალი, გთხოვთ»",
      "options": ["принесите холодную воду, пожалуйста", "дайте холодную воду, пожалуйста", "хочу холодную воду, пожалуйста"],
      "answer_index": 0,
      "explanation": "«მომიტანეთ ცივი წყალი, გთხოვთ» — принесите холодную воду, пожалуйста.",
      "tags": ["translation"],
      "difficulty": 2
    },
    {
      "id": "cafe5_q09",
      "lemma": "პური",
      "question": "Что из этого едят с каждым блюдом в Грузии?",
      "options": ["პური", "ტორტი", "ნაყინი"],
      "answer_index": 0,
      "explanation": "«პური» — хлеб. Хлеб в Грузии — обязательная часть любой трапезы.",
      "tags": ["context"],
      "difficulty": 1
    },
    {
      "id": "cafe5_q10",
      "lemma": "ღვინო",
      "question": "Переведи: «წითელი ღვინო მინდა, გთხოვთ»",
      "options": ["хочу красное вино, пожалуйста", "хочу белое вино, пожалуйста", "дайте красное вино, пожалуйста"],
      "answer_index": 0,
      "explanation": "«წითელი ღვინო მინდა, გთხოვთ» — хочу красное вино, пожалуйста. წითელი — красный.",
      "tags": ["translation"],
      "difficulty": 2
    },
    {
      "id": "cafe5_q11",
      "lemma": "მაგიდა",
      "question": "Ты входишь в ресторан. Как спросить про свободный столик?",
      "options": ["თავისუფალი მაგიდა არის?", "მენიუ არის?", "მიმტანი სად არის?"],
      "answer_index": 0,
      "explanation": "«თავისუფალი მაგიდა არის?» — есть свободный столик? თავისუფალი — свободный.",
      "tags": ["phrase"],
      "difficulty": 2
    },
    {
      "id": "cafe5_q12",
      "lemma": "საუზმე",
      "question": "В отеле в 8 утра. Куда идёшь?",
      "options": ["საუზმეზე", "სადილზე", "ბაზარში"],
      "answer_index": 0,
      "explanation": "«საუზმეზე» — на завтрак. Утром — საუზმე (завтрак).",
      "tags": ["context"],
      "difficulty": 1
    },
    {
      "id": "cafe5_q13",
      "lemma": "ძვირი",
      "question": "Переведи: «ეს ძალიან ძვირია»",
      "options": ["это очень дорого", "это очень дёшево", "это очень вкусно"],
      "answer_index": 0,
      "explanation": "«ეს ძალიან ძვირია» — это очень дорого. ძალიან — очень.",
      "tags": ["translation"],
      "difficulty": 2
    },
    {
      "id": "cafe5_q14",
      "lemma": "მადლობა",
      "question": "Диалог: Официант приносит еду. Ты говоришь:",
      "options": ["მადლობა!", "გთხოვთ!", "მინდა!"],
      "answer_index": 0,
      "explanation": "«მადლობა!» — спасибо! Не забывай благодарить.",
      "tags": ["context"],
      "difficulty": 1
    },
    {
      "id": "cafe5_q15",
      "lemma": "ხორცი",
      "question": "Переведи: «ცხელი ხორცი და ახალი პური»",
      "options": ["горячее мясо и свежий хлеб", "холодное мясо и свежий хлеб", "горячее мясо и вкусный хлеб"],
      "answer_index": 0,
      "explanation": "«ცხელი ხორცი და ახალი პური» — горячее мясо и свежий хлеб. და — и.",
      "tags": ["translation"],
      "difficulty": 2
    },
    {
      "id": "cafe5_q16",
      "lemma": "მიმტანი",
      "question": "Как позвать официанта?",
      "options": ["მიმტანი!", "მაგიდა!", "მენიუ!"],
      "answer_index": 0,
      "explanation": "«მიმტანი!» — официант! Можно также сказать «გთხოვთ!» (пожалуйста).",
      "tags": ["context"],
      "difficulty": 1
    },
    {
      "id": "cafe5_q17",
      "lemma": "იაფი",
      "question": "Торговец на рынке снизил цену. Теперь товар:",
      "options": ["იაფი", "ძვირი", "ახალი"],
      "answer_index": 0,
      "explanation": "«იაფი» — дешёвый. Антоним «ძვირი» (дорогой).",
      "tags": ["context"],
      "difficulty": 1
    },
    {
      "id": "cafe5_q18",
      "lemma": "თევზი",
      "question": "Составь заказ: «... და ყველი მინდა» — хочу рыбу и сыр",
      "options": ["თევზი", "ხორცი", "პური"],
      "answer_index": 0,
      "explanation": "«თევზი და ყველი მინდა» — хочу рыбу и сыр. თევზი — рыба, ყველი — сыр.",
      "tags": ["phrase"],
      "difficulty": 2
    }
  ]
}